junitmgr/__init__.py
junitmgr-1.0.3.data/scripts/junitmgr
junitmgr-1.0.3.dist-info/LICENSE
junitmgr-1.0.3.dist-info/METADATA
junitmgr-1.0.3.dist-info/WHEEL
junitmgr-1.0.3.dist-info/top_level.txt
junitmgr-1.0.3.dist-info/RECORD
