Metadata-Version: 2.1
Name: junitmgr
Version: 1.0.3
Summary: Manages Surefire XML (JUnit) XML files, especially huge files,, for generating reports.
Home-page: https://github.com/h20dragon/junitmgr.git
Author: H20Dragon
Author-email: h20dragon@outlook.com
License: Apache 2.0
Keywords: junit surefire nunit xunit xml parser h20dragon
Platform: UNKNOWN
Requires-Dist: future
Requires-Dist: junitparser
Requires-Dist: lxml
